setup.py
bullwinkle/__changelog__.py
bullwinkle/__init__.py
bullwinkle/__license__.py
bullwinkle/__test__.py
bullwinkle/__version__.py
bullwinkle/bwcached.py
bullwinkle/bwcontext.py
bullwinkle/bwconvertable.py
bullwinkle/bwmember.py
bullwinkle/bwmethod.py
bullwinkle/bwobject.py
bullwinkle/bwthrowable.py
bullwinkle/bwversion.py
bullwinkle.egg-info/PKG-INFO
bullwinkle.egg-info/SOURCES.txt
bullwinkle.egg-info/dependency_links.txt
bullwinkle.egg-info/top_level.txt