Metadata-Version: 1.0
Name: bullwinkle
Version: 0.3.4
Summary: Python tools inspired by Perl::Moose
Home-page: http://code.google.com/p/bullwinkle
Author: Rich Harkins
Author-email: rich.harkins@gmail.com
License: UNKNOWN
Keywords: Moose OOP super
Platform: UNKNOWN
Classifier: Development Status :: 2 - Pre-Alpha
Classifier: Intended Audience :: Developers
Classifier: License :: OSI Approved :: GNU Affero General Public License v3
Classifier: Programming Language :: Python
Classifier: Topic :: Utilities
